datanerd/__init__.py
datanerd/iv_woe.py
datanerd/notifier.py
datanerd/pushdb.py
datanerd/stats.py
datanerd-1.2.dist-info/METADATA
datanerd-1.2.dist-info/WHEEL
datanerd-1.2.dist-info/top_level.txt
datanerd-1.2.dist-info/RECORD
