Metadata-Version: 2.1
Name: datanerd
Version: 1.2
Summary: Contains multiple functions stats(), iv_woe(), pushdb(), teams_webhook(), and ntfy()
Home-page: UNKNOWN
Author: Sunil Aleti
Author-email: iam@sunilaleti.dev
License: UNKNOWN
Keywords: python,describe,stats,unique values,information value,woe,iv
Platform: UNKNOWN
Classifier: Programming Language :: Python :: 3
Classifier: License :: OSI Approved :: MIT License
Classifier: Operating System :: OS Independent
Requires-Dist: pandas
Requires-Dist: numpy
Requires-Dist: sqlalchemy
Requires-Dist: pyodbc
Requires-Dist: requests
